TeamNoob_WARP/__init__.py
TeamNoob_WARP/main.py
TeamNoob_WARP-0.1.5.dist-info/METADATA
TeamNoob_WARP-0.1.5.dist-info/WHEEL
TeamNoob_WARP-0.1.5.dist-info/entry_points.txt
TeamNoob_WARP-0.1.5.dist-info/top_level.txt
TeamNoob_WARP-0.1.5.dist-info/RECORD
