Metadata-Version: 2.1
Name: TeamNoob_WARP
Version: 0.1.5
Summary: A library for sending WARP MB using a referrer
Home-page: https://t.me/TeamNoob_Official
Author: GW ROHIT
Author-email: teamnoob909@gmail.com
Keywords: warp teamnoob cloudflare referrer unlimited mb rohit python library
Classifier: Programming Language :: Python :: 3
Classifier: Operating System :: OS Independent
Requires-Python: >=3.6
Requires-Dist: requests
Requires-Dist: python-cfonts
